django_metroui5-0.1.1.dist-info/licenses/LICENSE
metroui5/__about__.py
metroui5/__init__.py
metroui5/apps.py
metroui5/components.py
metroui5/core.py
metroui5/css.py
metroui5/forms.py
metroui5/html.py
metroui5/renderers.py
metroui5/static/metroui5/css/metro.all.css
metroui5/static/metroui5/icons/icons.css
metroui5/static/metroui5/icons/metro-ui-core.svg
metroui5/static/metroui5/icons/metro-ui-core.ttf
metroui5/static/metroui5/icons/metro-ui-core.woff
metroui5/static/metroui5/js/metro.all.js
metroui5/templates/metroui5/components/tile.html
metroui5/templates/metroui5/forms/field.html
metroui5/templates/metroui5/forms/form.html
metroui5/templates/metroui5/layout/base.html
metroui5/templatetags/__init__.py
metroui5/templatetags/metroui5.py
django_metroui5-0.1.1.dist-info/METADATA
django_metroui5-0.1.1.dist-info/WHEEL
django_metroui5-0.1.1.dist-info/top_level.txt
django_metroui5-0.1.1.dist-info/RECORD
