Metadata-Version: 2.4
Name: django-metroui5
Version: 0.1.1
Summary: MetroUI v5 integration for Django 4.1+
Home-page: https://github.com/DevCraftClub/django-metroui5
Author: Maxim Harder
Author-email: Maxim Harder <dev@devcraft.club>
Maintainer-email: Maxim Harder <dev@devcraft.club>
License: MIT
Project-URL: Homepage, https://github.com/DevCraftClub/django-metroui5
Project-URL: Documentation (Russian), https://readme.devcraft.club
Project-URL: Documentation (English), https://github.com/DevCraftClub/django-metroui5/docs/en/
Project-URL: Repository, https://github.com/DevCraftClub/django-metroui5.git
Project-URL: Bug Tracker, https://github.com/DevCraftClub/django-metroui5/issues
Keywords: django,metroui,ui,frontend,framework,bootstrap-replacement
Classifier: Development Status :: 3 - Alpha
Classifier: Environment :: Web Environment
Classifier: Framework :: Django
Classifier: Framework :: Django :: 4.1
Classifier: Framework :: Django :: 4.2
Classifier: Framework :: Django :: 5.0
Classifier: Framework :: Django :: 5.1
Classifier: Framework :: Django :: 5.2
Classifier: Intended Audience :: Developers
Classifier: License :: OSI Approved :: MIT License
Classifier: Operating System :: OS Independent
Classifier: Programming Language :: Python
Classifier: Programming Language :: Python :: 3
Classifier: Programming Language :: Python :: 3.9
Classifier: Programming Language :: Python :: 3.10
Classifier: Programming Language :: Python :: 3.11
Classifier: Programming Language :: Python :: 3.12
Classifier: Programming Language :: Python :: 3.13
Classifier: Topic :: Internet :: WWW/HTTP
Classifier: Topic :: Internet :: WWW/HTTP :: Dynamic Content
Classifier: Topic :: Software Development :: Libraries :: Python Modules
Requires-Python: >=3.9
License-File: LICENSE
Requires-Dist: Django>=4.2
Provides-Extra: dev
Requires-Dist: pytest>=7.0.0; extra == "dev"
Requires-Dist: pytest-django>=4.5.0; extra == "dev"
Requires-Dist: mypy>=1.0.0; extra == "dev"
Dynamic: author
Dynamic: home-page
Dynamic: license-file
Dynamic: requires-python
